{
    "groups": [["animal", "生物"], ["machine", "机械"], ["building", "建筑"], ["fly", "飞行"], ["huge", "巨型"], ["hero", "英雄"]],
    "armors": ["轻甲", "重甲", "无甲"],
    "units": [
        {
            "name": "陆战队员",
            "nick": "枪兵、机枪",
            "attr": "45,0|6|0,2|5,5|0.61",
            "group": "100000",
            "skill": "兴奋剂：消耗10点生命在一段时间内提升攻速和移速",
            "comment": ""
        }, {
            "name": "死神",
            "nick": "",
            "attr": "60,0|4*2|0,2|5,-1|0.79",
            "group": "100000",
            "skill": "手雷：短暂延迟后造成5范围伤害并击退单位，冷却14秒。战斗药剂：脱离战斗后会恢复生命",
            "comment": ""
        }
    ]
}